reqproxy/__init__.py
reqproxy/exceptions.py
reqproxy/proxy_requests.py
reqproxy-0.1.0.dist-info/METADATA
reqproxy-0.1.0.dist-info/WHEEL
reqproxy-0.1.0.dist-info/entry_points.txt
reqproxy-0.1.0.dist-info/RECORD
