Metadata-Version: 2.4
Name: reqproxy
Version: 0.1.0
Summary: A Python library for making HTTP requests through a rotating set of proxies.
Author-email: Kamal <kamal.farahani90@gmail.com>
Requires-Python: >=3.12
Requires-Dist: requests>=2.32.3
